holiday_calendar
