Metadata-Version: 2.1
Name: holiday-calendar
Version: 0.1.3
Summary: The holidays in China
Home-page: https://github.com/Thchoonlophon/holiday_calendar
Author: Jingxuan
Author-email: qian_chen_jin@163.com
License: MIT License
Platform: UNKNOWN
Classifier: License :: OSI Approved :: MIT License
Classifier: Programming Language :: Python :: 3
Classifier: Programming Language :: Python :: 3.6
Classifier: Programming Language :: Python :: 3.7
Classifier: Programming Language :: Python :: 3.8
